{
    "common": {
        "name": "tuya",
        "version": "3.5.2",
        "news": {
            "3.5.2": {
                "en": "More schema information added",
                "de": "Weitere Schemainformationen hinzugefügt",
                "ru": "Добавлена дополнительная информация о схеме",
                "pt": "Mais informações de esquema adicionadas",
                "nl": "Meer schema-informatie toegevoegd",
                "fr": "Plus d'informations sur le schéma ajoutées",
                "it": "Aggiunte ulteriori informazioni sullo schema",
                "es": "Se agregó más información de esquema",
                "pl": "Dodano więcej informacji o schemacie",
                "zh-cn": "添加了更多架构信息"
            },
            "3.5.0": {
                "en": "More schema information added\nTry to decode \"raw\" values via base64",
                "de": "Weitere Schemainformationen hinzugefügt\nVersuchen Sie, \"rohe\" Werte über base64 zu dekodieren",
                "ru": "Добавлена дополнительная информация о схеме\nПопробуйте декодировать \"сырые\" значения через base64",
                "pt": "Mais informações de esquema adicionadas\nTente decodificar valores \"brutos\" via base64",
                "nl": "Meer schema-informatie toegevoegd\nProbeer \"ruwe\" waarden te decoderen via base64",
                "fr": "Plus d'informations sur le schéma ajoutées\nEssayez de décoder les valeurs \"brutes\" via base64",
                "it": "Aggiunte ulteriori informazioni sullo schema\nProva a decodificare i valori \"grezzi\" tramite base64",
                "es": "Se agregó más información de esquema\nIntente decodificar valores \"sin procesar\" a través de base64",
                "pl": "Dodano więcej informacji o schemacie\nSpróbuj zdekodować „surowe” wartości przez base64",
                "zh-cn": "添加了更多架构信息\n尝试通过base64解码“原始”值"
            },
            "3.4.3": {
                "en": "More schema information added",
                "de": "Weitere Schemainformationen hinzugefügt",
                "ru": "Добавлена дополнительная информация о схеме",
                "pt": "Mais informações de esquema adicionadas",
                "nl": "Meer schema-informatie toegevoegd",
                "fr": "Plus d'informations sur le schéma ajoutées",
                "it": "Aggiunte ulteriori informazioni sullo schema",
                "es": "Se agregó más información de esquema",
                "pl": "Dodano więcej informacji o schemacie",
                "zh-cn": "添加了更多架构信息"
            },
            "3.4.2": {
                "en": "More schema information added",
                "de": "Weitere Schemainformationen hinzugefügt",
                "ru": "Добавлена дополнительная информация о схеме",
                "pt": "Mais informações de esquema adicionadas",
                "nl": "Meer schema-informatie toegevoegd",
                "fr": "Plus d'informations sur le schéma ajoutées",
                "it": "Aggiunte ulteriori informazioni sullo schema",
                "es": "Se agregó más información de esquema",
                "pl": "Dodano więcej informacji o schemacie",
                "zh-cn": "添加了更多架构信息"
            },
            "3.4.1": {
                "en": "More schema information added\nfix IP lookup via UDP",
                "de": "Weitere Schemainformationen hinzugefügt\nIP-Suche über UDP korrigieren",
                "ru": "Добавлена дополнительная информация о схеме\nисправить поиск IP через UDP",
                "pt": "Mais informações de esquema adicionadas\ncorrigir pesquisa de IP via UDP",
                "nl": "Meer schema-informatie toegevoegd\nIP-lookup repareren via UDP",
                "fr": "Plus d'informations sur le schéma ajoutées\ncorriger la recherche IP via UDP",
                "it": "Aggiunte ulteriori informazioni sullo schema\ncorreggere la ricerca IP tramite UDP",
                "es": "Se agregó más información de esquema\narreglar la búsqueda de IP a través de UDP",
                "pl": "Dodano więcej informacji o schemacie\nnaprawić wyszukiwanie IP przez UDP",
                "zh-cn": "添加了更多架构信息\n通过UDP修复IP查找"
            },
            "3.4.0": {
                "en": "update tuya-api library",
                "de": "Aktualisieren Sie die Tuya-API-Bibliothek",
                "ru": "обновить библиотеку tuya-api",
                "pt": "atualizar biblioteca tuya-api",
                "nl": "update tuya-api bibliotheek",
                "fr": "mettre à jour la bibliothèque tuya-api",
                "it": "aggiorna la libreria tuya-api",
                "es": "actualizar la biblioteca tuya-api",
                "pl": "zaktualizuj bibliotekę tuya-api",
                "zh-cn": "更新tuya-api库"
            },
            "3.3.15": {
                "en": "More schema information added",
                "de": "Weitere Schemainformationen hinzugefügt",
                "ru": "Добавлена дополнительная информация о схеме",
                "pt": "Mais informações de esquema adicionadas",
                "nl": "Meer schema-informatie toegevoegd",
                "fr": "Plus d'informations sur le schéma ajoutées",
                "it": "Aggiunte ulteriori informazioni sullo schema",
                "es": "Se agregó más información de esquema",
                "pl": "Dodano więcej informacji o schemacie",
                "zh-cn": "添加了更多架构信息"
            },
            "3.3.14": {
                "en": "More schema information added",
                "de": "Weitere Schemainformationen hinzugefügt",
                "ru": "Добавлена дополнительная информация о схеме",
                "pt": "Mais informações de esquema adicionadas",
                "nl": "Meer schema-informatie toegevoegd",
                "fr": "Plus d'informations sur le schéma ajoutées",
                "it": "Aggiunte ulteriori informazioni sullo schema",
                "es": "Se agregó más información de esquema",
                "pl": "Dodano więcej informacji o schemacie",
                "zh-cn": "添加了更多架构信息"
            },
            "3.3.13": {
                "en": "More schema information added",
                "de": "Weitere Schemainformationen hinzugefügt",
                "ru": "Добавлена дополнительная информация о схеме",
                "pt": "Mais informações de esquema adicionadas",
                "nl": "Meer schema-informatie toegevoegd",
                "fr": "Plus d'informations sur le schéma ajoutées",
                "it": "Aggiunte ulteriori informazioni sullo schema",
                "es": "Se agregó más información de esquema",
                "pl": "Dodano więcej informacji o schemacie",
                "zh-cn": "添加了更多架构信息"
            },
            "3.3.12": {
                "en": "More schema information added\nCrash case prevented (Sentry IOBROKER-TUYA-89)",
                "de": "Weitere Schemainformationen hinzugefügt\nAbsturzfall verhindert (Sentry IOBROKER-TUYA-89)",
                "ru": "Добавлена дополнительная информация о схеме\nПредотвращена авария (Sentry IOBROKER-TUYA-89)",
                "pt": "Mais informações de esquema adicionadas\nCaso de falha evitado (Sentry IOBROKER-TUYA-89)",
                "nl": "Meer schema-informatie toegevoegd\nCrashcase voorkomen (Sentry IOBROKER-TUYA-89)",
                "fr": "Plus d'informations sur le schéma ajoutées\nCrash case évité (Sentry IOBROKER-TUYA-89)",
                "it": "Aggiunte ulteriori informazioni sullo schema\nCrash case prevenuto (Sentry IOBROKER-TUYA-89)",
                "es": "Se agregó más información de esquema\nCaso de choque evitado (Sentry IOBROKER-TUYA-89)",
                "pl": "Dodano więcej informacji o schemacie\nZapobiegano awariom (Sentry IOBROKER-TUYA-89)",
                "zh-cn": "添加了更多架构信息\n避免发生崩溃情况（Sentry IOBROKER-TUYA-89）"
            },
            "3.3.11": {
                "en": "More schema information added",
                "de": "Weitere Schemainformationen hinzugefügt",
                "ru": "Добавлена дополнительная информация о схеме",
                "pt": "Mais informações de esquema adicionadas",
                "nl": "Meer schema-informatie toegevoegd",
                "fr": "Plus d'informations sur le schéma ajoutées",
                "it": "Aggiunte ulteriori informazioni sullo schema",
                "es": "Se agregó más información de esquema",
                "pl": "Dodano więcej informacji o schemacie",
                "zh-cn": "添加了更多架构信息"
            },
            "3.3.10": {
                "en": "More schema information added",
                "de": "Weitere Schemainformationen hinzugefügt",
                "ru": "Добавлена дополнительная информация о схеме",
                "pt": "Mais informações do esquema adicionadas",
                "nl": "Meer schema-informatie toegevoegd",
                "fr": "Plus d'informations sur le schéma ajoutées",
                "it": "Ulteriori informazioni sullo schema aggiunte",
                "es": "Se agregó más información de esquema",
                "pl": "Dodano więcej informacji o schemacie",
                "zh-cn": "添加了更多架构信息"
            },
            "3.3.9": {
                "en": "More schema information added",
                "de": "Weitere Schemainformationen hinzugefügt",
                "ru": "Добавлена дополнительная информация о схеме",
                "pt": "Mais informações do esquema adicionadas",
                "nl": "Meer schema-informatie toegevoegd",
                "fr": "Plus d'informations sur le schéma ajoutées",
                "it": "Ulteriori informazioni sullo schema aggiunte",
                "es": "Se agregó más información de esquema",
                "pl": "Dodano więcej informacji o schemacie",
                "zh-cn": "添加了更多架构信息"
            },
            "3.3.8": {
                "en": "Work around invalid data that are returned by some devices\nMore schema information added",
                "de": "Umgehen Sie ungültige Daten, die von einigen Geräten zurückgegeben werden\nWeitere Schemainformationen hinzugefügt",
                "ru": "Обход недопустимых данных, возвращаемых некоторыми устройствами\nДобавлена дополнительная информация о схеме",
                "pt": "Solução alternativa de dados inválidos retornados por alguns dispositivos\nMais informações do esquema adicionadas",
                "nl": "Omzeil ongeldige gegevens die door sommige apparaten worden geretourneerd\nMeer schema-informatie toegevoegd",
                "fr": "Contournement des données non valides renvoyées par certains appareils\nPlus d'informations sur le schéma ajoutées",
                "it": "Aggirare i dati non validi restituiti da alcuni dispositivi\nUlteriori informazioni sullo schema aggiunte",
                "es": "Evite datos no válidos que algunos dispositivos devuelven\nSe agregó más información de esquema",
                "pl": "Obejdź nieprawidłowe dane zwracane przez niektóre urządzenia\nDodano więcej informacji o schemacie",
                "zh-cn": "解决某些设备返回的无效数据\n添加了更多架构信息"
            },
            "3.3.7": {
                "en": "More schema information added",
                "de": "Weitere Schemainformationen hinzugefügt",
                "ru": "Добавлена дополнительная информация о схеме",
                "pt": "Mais informações do esquema adicionadas",
                "nl": "Meer schema-informatie toegevoegd",
                "fr": "Plus d'informations sur le schéma ajoutées",
                "it": "Ulteriori informazioni sullo schema aggiunte",
                "es": "Se agregó más información de esquema",
                "pl": "Dodano więcej informacji o schemacie",
                "zh-cn": "添加了更多架构信息"
            },
            "3.3.6": {
                "en": "More schema information added",
                "de": "Weitere Schemainformationen hinzugefügt",
                "ru": "Добавлена дополнительная информация о схеме",
                "pt": "Mais informações do esquema adicionadas",
                "nl": "Meer schema-informatie toegevoegd",
                "fr": "Plus d'informations sur le schéma ajoutées",
                "it": "Ulteriori informazioni sullo schema aggiunte",
                "es": "Se agregó más información de esquema",
                "pl": "Dodano więcej informacji o schemacie",
                "zh-cn": "添加了更多架构信息"
            },
            "3.3.5": {
                "en": "More schema information added\nOptimizations and fixes",
                "de": "Weitere Schemainformationen hinzugefügt\nOptimierungen und Korrekturen",
                "ru": "Добавлена дополнительная информация о схеме\nОптимизации и исправления",
                "pt": "Mais informações do esquema adicionadas\nOtimizações e correções",
                "nl": "Meer schema-informatie toegevoegd\nOptimalisaties en oplossingen",
                "fr": "Plus d'informations sur le schéma ajoutées\nOptimisations et correctifs",
                "it": "Ulteriori informazioni sullo schema aggiunte\nOttimizzazioni e correzioni",
                "es": "Se agregó más información de esquema\nOptimizaciones y arreglos",
                "pl": "Dodano więcej informacji o schemacie\nOptymalizacje i poprawki",
                "zh-cn": "添加了更多架构信息\n优化和修复"
            },
            "3.2.3": {
                "en": "More schema information added",
                "de": "Weitere Schemainformationen hinzugefügt",
                "ru": "Добавлена дополнительная информация о схеме",
                "pt": "Mais informações do esquema adicionadas",
                "nl": "Meer schema-informatie toegevoegd",
                "fr": "Plus d'informations sur le schéma ajoutées",
                "it": "Ulteriori informazioni sullo schema aggiunte",
                "es": "Se agregó más información de esquema",
                "pl": "Dodano więcej informacji o schemacie",
                "zh-cn": "添加了更多架构信息"
            },
            "3.2.2": {
                "en": "More schema information added, further fixes and optimizations",
                "de": "Weitere Schemainformationen hinzugefügt, weitere Korrekturen und Optimierungen",
                "ru": "Добавлена дополнительная информация о схеме, дополнительные исправления и оптимизации",
                "pt": "Mais informações sobre o esquema adicionadas, correções e otimizações adicionais",
                "nl": "Meer schema-informatie toegevoegd, verdere fixes en optimalisaties",
                "fr": "Plus d'informations sur le schéma ajoutées, corrections et optimisations supplémentaires",
                "it": "Ulteriori informazioni sullo schema aggiunte, ulteriori correzioni e ottimizzazioni",
                "es": "Se agregó más información de esquema, más correcciones y optimizaciones",
                "pl": "Dodano więcej informacji o schemacie, dalsze poprawki i optymalizacje",
                "zh-cn": "添加了更多架构信息，进一步的修复和优化"
            },
            "3.2.0": {
                "en": "More schema information added",
                "de": "Weitere Schemainformationen hinzugefügt",
                "ru": "Добавлена дополнительная информация о схеме",
                "pt": "Mais informações do esquema adicionadas",
                "nl": "Meer schema-informatie toegevoegd",
                "fr": "Plus d'informations sur le schéma ajoutées",
                "it": "Ulteriori informazioni sullo schema aggiunte",
                "es": "Se agregó más información de esquema",
                "pl": "Dodano więcej informacji o schemacie",
                "zh-cn": "添加了更多架构信息"
            }
        },
        "title": "Tuya",
        "titleLang": {
            "en": "Tuya",
            "de": "Tuya",
            "ru": "Tuya",
            "pt": "Tuya",
            "nl": "Tuya",
            "fr": "Tuya",
            "it": "Tuya",
            "es": "Tuya",
            "pl": "Tuya"
        },
        "desc": {
            "en": "Tuya Adapter",
            "de": "Tuya Adapter",
            "ru": "Tuya адаптер",
            "pt": "Adaptador Tuya",
            "nl": "Tuya-adapter",
            "fr": "Adaptateur Tuya",
            "it": "Adattatore Tuya",
            "es": "Adaptador Tuya",
            "pl": "Adapter Tuya"
        },
        "license": "MIT",
        "authors": [
            "Apollon77 <iobroker@fischer-ka.de>"
        ],
        "platform": "Javascript/Node.js",
        "mode": "daemon",
        "icon": "tuya.png",
        "messagebox": true,
        "subscribe": "messagebox",
        "materialize": true,
        "enabled": true,
        "extIcon": "https://raw.githubusercontent.com/Apollon77/ioBroker.tuya/master/admin/tuya.png",
        "keywords": [
            "Tuya",
            "switch",
            "smarthome",
            "iobroker"
        ],
        "readme": "https://github.com/Apollon77/ioBroker.tuya/blob/master/README.md",
        "loglevel": "info",
        "type": "iot-systems",
        "restartAdapters": [],
        "stopTimeout": 5000,
        "compact": true,
        "dependencies": [
            {
                "js-controller": ">=2.0.0"
            }
        ],
        "plugins": {
            "sentry": {
                "dsn": "https://35b8ba3898fa4dda82327af26ea8e807@sentry.iobroker.net/6",
                "pathWhitelist": [
                    "@apollon"
                ],
                "errorBlacklist": [
                    "SyntaxError"
                ]
            }
        }
    },
    "native": {
        "pollingInterval": 60,
        "proxyPort": 8888,
        "proxyWebPort": 8889
    },
    "objects": [],
    "instanceObjects": [
        {
            "_id": "info",
            "type": "channel",
            "common": {
                "name": "Information"
            },
            "native": {}
        },
        {
            "_id": "info.connection",
            "type": "state",
            "common": {
                "role": "indicator.connected",
                "name": "If connected to Tuya devices",
                "type": "boolean",
                "read": true,
                "write": false,
                "def": false
            },
            "native": {}
        }
    ]
}